<annotation verified="yes"><folder>images</folder><filename>00000990.jpg</filename><path>home/cyber/vedai/images/00000990.jpg</path><source><database>Unknown</database></source><size><width>1024</width><height>1024</height><depth>3</depth></size><segmented>0</segmented><object><name>car</name><pose>Unspecified</pose><truncated>0</truncated><difficult>0</difficult><bndbox><xmin>169</xmin><ymin>38</ymin><xmax>187</xmax><ymax>80</ymax></bndbox></object><object><name>car</name><pose>Unspecified</pose><truncated>0</truncated><difficult>0</difficult><bndbox><xmin>652</xmin><ymin>670</ymin><xmax>668</xmax><ymax>707</ymax></bndbox></object></annotation>