<annotation verified="yes"><folder>images</folder><filename>00000298.jpg</filename><path>home/cyber/vedai/images/00000298.jpg</path><source><database>Unknown</database></source><size><width>1024</width><height>1024</height><depth>3</depth></size><segmented>0</segmented><object><name>pickup</name><pose>Unspecified</pose><truncated>0</truncated><difficult>0</difficult><bndbox><xmin>59</xmin><ymin>237</ymin><xmax>98</xmax><ymax>272</ymax></bndbox></object><object><name>pickup</name><pose>Unspecified</pose><truncated>0</truncated><difficult>0</difficult><bndbox><xmin>696</xmin><ymin>662</ymin><xmax>738</xmax><ymax>679</ymax></bndbox></object><object><name>tractor</name><pose>Unspecified</pose><truncated>0</truncated><difficult>0</difficult><bndbox><xmin>128</xmin><ymin>829</ymin><xmax>162</xmax><ymax>859</ymax></bndbox></object></annotation>