<annotation verified="yes"><folder>images</folder><filename>00000262.jpg</filename><path>home/cyber/vedai/images/00000262.jpg</path><source><database>Unknown</database></source><size><width>1024</width><height>1024</height><depth>3</depth></size><segmented>0</segmented><object><name>camping car</name><pose>Unspecified</pose><truncated>0</truncated><difficult>0</difficult><bndbox><xmin>89</xmin><ymin>383</ymin><xmax>153</xmax><ymax>404</ymax></bndbox></object><object><name>car</name><pose>Unspecified</pose><truncated>0</truncated><difficult>0</difficult><bndbox><xmin>238</xmin><ymin>279</ymin><xmax>257</xmax><ymax>323</ymax></bndbox></object><object><name>car</name><pose>Unspecified</pose><truncated>0</truncated><difficult>0</difficult><bndbox><xmin>385</xmin><ymin>-3</ymin><xmax>422</xmax><ymax>22</ymax></bndbox></object><object><name>boat</name><pose>Unspecified</pose><truncated>0</truncated><difficult>0</difficult><bndbox><xmin>847</xmin><ymin>43</ymin><xmax>874</xmax><ymax>81</ymax></bndbox></object></annotation>