<annotation verified="yes"><folder>images</folder><filename>00000070.jpg</filename><path>home/cyber/vedai/images/00000070.jpg</path><source><database>Unknown</database></source><size><width>1024</width><height>1024</height><depth>3</depth></size><segmented>0</segmented><object><name>truck</name><pose>Unspecified</pose><truncated>0</truncated><difficult>0</difficult><bndbox><xmin>560</xmin><ymin>305</ymin><xmax>624</xmax><ymax>330</ymax></bndbox></object><object><name>pickup</name><pose>Unspecified</pose><truncated>0</truncated><difficult>0</difficult><bndbox><xmin>478</xmin><ymin>720</ymin><xmax>498</xmax><ymax>768</ymax></bndbox></object></annotation>