<annotation verified="yes"><folder>images</folder><filename>00000831.jpg</filename><path>home/cyber/vedai/images/00000831.jpg</path><source><database>Unknown</database></source><size><width>1024</width><height>1024</height><depth>3</depth></size><segmented>0</segmented><object><name>car</name><pose>Unspecified</pose><truncated>0</truncated><difficult>0</difficult><bndbox><xmin>281</xmin><ymin>274</ymin><xmax>310</xmax><ymax>309</ymax></bndbox></object><object><name>car</name><pose>Unspecified</pose><truncated>0</truncated><difficult>0</difficult><bndbox><xmin>283</xmin><ymin>689</ymin><xmax>306</xmax><ymax>728</ymax></bndbox></object><object><name>camping car</name><pose>Unspecified</pose><truncated>0</truncated><difficult>0</difficult><bndbox><xmin>945</xmin><ymin>366</ymin><xmax>972</xmax><ymax>437</ymax></bndbox></object></annotation>