<annotation verified="yes"><folder>images</folder><filename>00000616.jpg</filename><path>home/cyber/vedai/images/00000616.jpg</path><source><database>Unknown</database></source><size><width>1024</width><height>1024</height><depth>3</depth></size><segmented>0</segmented><object><name>pickup</name><pose>Unspecified</pose><truncated>0</truncated><difficult>0</difficult><bndbox><xmin>373</xmin><ymin>537</ymin><xmax>393</xmax><ymax>580</ymax></bndbox></object><object><name>car</name><pose>Unspecified</pose><truncated>0</truncated><difficult>0</difficult><bndbox><xmin>370</xmin><ymin>319</ymin><xmax>388</xmax><ymax>359</ymax></bndbox></object></annotation>