<annotation verified="yes"><folder>images</folder><filename>00001121.jpg</filename><path>home/cyber/vedai/images/00001121.jpg</path><source><database>Unknown</database></source><size><width>1024</width><height>1024</height><depth>3</depth></size><segmented>0</segmented><object><name>car</name><pose>Unspecified</pose><truncated>0</truncated><difficult>0</difficult><bndbox><xmin>147</xmin><ymin>161</ymin><xmax>192</xmax><ymax>176</ymax></bndbox></object><object><name>pickup</name><pose>Unspecified</pose><truncated>0</truncated><difficult>0</difficult><bndbox><xmin>493</xmin><ymin>266</ymin><xmax>517</xmax><ymax>309</ymax></bndbox></object><object><name>pickup</name><pose>Unspecified</pose><truncated>0</truncated><difficult>0</difficult><bndbox><xmin>677</xmin><ymin>261</ymin><xmax>702</xmax><ymax>310</ymax></bndbox></object><object><name>car</name><pose>Unspecified</pose><truncated>0</truncated><difficult>0</difficult><bndbox><xmin>607</xmin><ymin>266</ymin><xmax>625</xmax><ymax>308</ymax></bndbox></object><object><name>car</name><pose>Unspecified</pose><truncated>0</truncated><difficult>0</difficult><bndbox><xmin>937</xmin><ymin>210</ymin><xmax>977</xmax><ymax>225</ymax></bndbox></object></annotation>