<annotation verified="yes"><folder>images</folder><filename>00001114.jpg</filename><path>home/cyber/vedai/images/00001114.jpg</path><source><database>Unknown</database></source><size><width>1024</width><height>1024</height><depth>3</depth></size><segmented>0</segmented><object><name>tractor</name><pose>Unspecified</pose><truncated>0</truncated><difficult>0</difficult><bndbox><xmin>731</xmin><ymin>290</ymin><xmax>759</xmax><ymax>322</ymax></bndbox></object><object><name>car</name><pose>Unspecified</pose><truncated>0</truncated><difficult>0</difficult><bndbox><xmin>387</xmin><ymin>367</ymin><xmax>418</xmax><ymax>419</ymax></bndbox></object><object><name>pickup</name><pose>Unspecified</pose><truncated>0</truncated><difficult>0</difficult><bndbox><xmin>246</xmin><ymin>330</ymin><xmax>291</xmax><ymax>347</ymax></bndbox></object><object><name>car</name><pose>Unspecified</pose><truncated>0</truncated><difficult>0</difficult><bndbox><xmin>207</xmin><ymin>356</ymin><xmax>243</xmax><ymax>374</ymax></bndbox></object></annotation>