<annotation verified="yes"><folder>images</folder><filename>image.jpg</filename><path>/home/cyber/vedai/cowc_image/imageimage.jpg</path><source><database>Unknown</database></source><size><width>1024</width><height>1024</height><depth>3</depth></size><segmented>0</segmented><object><name>car</name><pose>Unspecified</pose><truncated>0</truncated><difficult>0</difficult><bndbox><xmin>180</xmin><ymin>677</ymin><xmax>214</xmax><ymax>711</ymax></bndbox></object><object><name>car</name><pose>Unspecified</pose><truncated>0</truncated><difficult>0</difficult><bndbox><xmin>180</xmin><ymin>678</ymin><xmax>214</xmax><ymax>712</ymax></bndbox></object><object><name>car</name><pose>Unspecified</pose><truncated>0</truncated><difficult>0</difficult><bndbox><xmin>66</xmin><ymin>800</ymin><xmax>100</xmax><ymax>834</ymax></bndbox></object><object><name>car</name><pose>Unspecified</pose><truncated>0</truncated><difficult>0</difficult><bndbox><xmin>322</xmin><ymin>829</ymin><xmax>356</xmax><ymax>863</ymax></bndbox></object><object><name>car</name><pose>Unspecified</pose><truncated>0</truncated><difficult>0</difficult><bndbox><xmin>322</xmin><ymin>866</ymin><xmax>356</xmax><ymax>900</ymax></bndbox></object><object><name>car</name><pose>Unspecified</pose><truncated>0</truncated><difficult>0</difficult><bndbox><xmin>79</xmin><ymin>874</ymin><xmax>113</xmax><ymax>908</ymax></bndbox></object><object><name>car</name><pose>Unspecified</pose><truncated>0</truncated><difficult>0</difficult><bndbox><xmin>219</xmin><ymin>877</ymin><xmax>253</xmax><ymax>911</ymax></bndbox></object><object><name>car</name><pose>Unspecified</pose><truncated>0</truncated><difficult>0</difficult><bndbox><xmin>180</xmin><ymin>879</ymin><xmax>214</xmax><ymax>913</ymax></bndbox></object><object><name>car</name><pose>Unspecified</pose><truncated>0</truncated><difficult>0</difficult><bndbox><xmin>324</xmin><ymin>884</ymin><xmax>358</xmax><ymax>918</ymax></bndbox></object><object><name>car</name><pose>Unspecified</pose><truncated>0</truncated><difficult>0</difficult><bndbox><xmin>178</xmin><ymin>895</ymin><xmax>212</xmax><ymax>929</ymax></bndbox></object><object><name>car</name><pose>Unspecified</pose><truncated>0</truncated><difficult>0</difficult><bndbox><xmin>221</xmin><ymin>895</ymin><xmax>255</xmax><ymax>929</ymax></bndbox></object><object><name>car</name><pose>Unspecified</pose><truncated>0</truncated><difficult>0</difficult><bndbox><xmin>319</xmin><ymin>906</ymin><xmax>353</xmax><ymax>940</ymax></bndbox></object><object><name>car</name><pose>Unspecified</pose><truncated>0</truncated><difficult>0</difficult><bndbox><xmin>28</xmin><ymin>969</ymin><xmax>62</xmax><ymax>1003</ymax></bndbox></object><object><name>car</name><pose>Unspecified</pose><truncated>0</truncated><difficult>0</difficult><bndbox><xmin>25</xmin><ymin>987</ymin><xmax>59</xmax><ymax>1021</ymax></bndbox></object></annotation>