<annotation verified="yes"><folder>256</folder><filename>403.jpg</filename><path>/home/cyber/clone_vedai/vedai/cowc/256/403.jpg</path><source><database>Unknown</database></source><size><width>256</width><height>256</height><depth>3</depth></size><segmented>0</segmented><object><name>car</name><pose>Unspecified</pose><truncated>0</truncated><difficult>0</difficult><bndbox><xmin>16</xmin><ymin>0</ymin><xmax>37</xmax><ymax>19</ymax></bndbox></object><object><name>car</name><pose>Unspecified</pose><truncated>0</truncated><difficult>0</difficult><bndbox><xmin>36</xmin><ymin>0</ymin><xmax>56</xmax><ymax>26</ymax></bndbox></object><object><name>car</name><pose>Unspecified</pose><truncated>0</truncated><difficult>0</difficult><bndbox><xmin>177</xmin><ymin>42</ymin><xmax>195</xmax><ymax>75</ymax></bndbox></object><object><name>car</name><pose>Unspecified</pose><truncated>0</truncated><difficult>0</difficult><bndbox><xmin>230</xmin><ymin>61</ymin><xmax>247</xmax><ymax>93</ymax></bndbox></object><object><name>car</name><pose>Unspecified</pose><truncated>0</truncated><difficult>0</difficult><bndbox><xmin>0</xmin><ymin>230</ymin><xmax>34</xmax><ymax>253</ymax></bndbox></object></annotation>